flux_metrics_api/__init__.py
flux_metrics_api/apis.py
flux_metrics_api/defaults.py
flux_metrics_api/logger.py
flux_metrics_api/metrics.py
flux_metrics_api/routes.py
flux_metrics_api/server.py
flux_metrics_api/types.py
flux_metrics_api/utils.py
flux_metrics_api/version.py
flux_metrics_api-0.0.11.dist-info/LICENSE
flux_metrics_api-0.0.11.dist-info/METADATA
flux_metrics_api-0.0.11.dist-info/NOTICE
flux_metrics_api-0.0.11.dist-info/WHEEL
flux_metrics_api-0.0.11.dist-info/entry_points.txt
flux_metrics_api-0.0.11.dist-info/top_level.txt
flux_metrics_api-0.0.11.dist-info/RECORD
