Metadata-Version: 2.1
Name: flux-metrics-api
Version: 0.0.11
Summary: Custom metrics exporter for Flux in Kubernetes
Home-page: https://github.com/converged-computing/flux-metrics-api
Author: Vanessa Sochat
Author-email: vsoch@users.noreply.github.com
Maintainer: Vanessa Sochat
License: LICENSE
Keywords: cloud,flux,flux-framework,monitoring
Classifier: Intended Audience :: Science/Research
Classifier: Intended Audience :: Developers
Classifier: License :: OSI Approved :: MIT License
Classifier: Programming Language :: Python
Classifier: Topic :: Software Development
Classifier: Topic :: Scientific/Engineering
Classifier: Operating System :: Unix
Classifier: Programming Language :: Python :: 3.8
License-File: LICENSE
License-File: NOTICE
Requires-Dist: uvicorn
Requires-Dist: starlette
Requires-Dist: starlette-apispec
Provides-Extra: all
Requires-Dist: uvicorn ; extra == 'all'
Requires-Dist: starlette ; extra == 'all'
Requires-Dist: starlette-apispec ; extra == 'all'
